{"file":"mapView.png","frames":{
"advatureButton":{"x":1,"y":1,"w":100,"h":50,"_3595":0,"_3594":0,"sourceW":100,"sourceH":50},
"select":{"x":1,"y":53,"w":48,"h":48,"_3595":0,"_3594":0,"sourceW":48,"sourceH":48},
"infiniteButton":{"x":1,"y":103,"w":100,"h":50,"_3595":0,"_3594":0,"sourceW":100,"sourceH":50},
"grid":{"x":1,"y":155,"w":480,"h":480,"_3595":0,"_3594":0,"sourceW":480,"sourceH":480},
"hitBody":{"x":51,"y":53,"w":48,"h":48,"_3595":0,"_3594":0,"sourceW":48,"sourceH":48},
"hitHead":{"x":101,"y":53,"w":48,"h":48,"_3595":0,"_3594":0,"sourceW":48,"sourceH":48},
"hitHole":{"x":103,"y":1,"w":48,"h":48,"_3595":0,"_3594":0,"sourceW":48,"sourceH":48},
"panel":{"x":1,"y":637,"w":480,"h":250,"_3595":0,"_3594":0,"sourceW":480,"sourceH":250}}}